omniml/__init__.py
omniml-0.1.0.dist-info/LICENSE
omniml-0.1.0.dist-info/METADATA
omniml-0.1.0.dist-info/WHEEL
omniml-0.1.0.dist-info/RECORD
